README.md
setup.py
guess_logo/__init__.py
guess_logo/color.py
guess_logo/guess_logo.py
guess_logo/logo.py
guess_logo.egg-info/PKG-INFO
guess_logo.egg-info/SOURCES.txt
guess_logo.egg-info/dependency_links.txt
guess_logo.egg-info/requires.txt
guess_logo.egg-info/top_level.txt
guess_logo.egg-info/zip-safe