Metadata-Version: 1.1
Name: guess-logo
Version: 0.0.7
Summary: Detect logo url for any website.
Home-page: https://github.com/KehaoWu/guess_logo
Author: Kehao Wu
Author-email: kehao.wu@gmail.com
License: MIT
Keywords: guess logo website selenium
Platform: UNKNOWN
Classifier: Development Status :: 5 - Production/Stable
Classifier: License :: OSI Approved :: Apache Software License
Classifier: Programming Language :: Python :: 3.5
Classifier: Programming Language :: SQL
Classifier: Topic :: Database
